{
  "model_number": "I3MZ-WRAUWZ",
  "title": "I3MZ-WRAUWZ - Protection relay, EOCR Digital, 0.5 to 60A, 100 to 240VAC/DC, window connt, for motor protection",
  "range_name": "EOCR",
  "range_short_desc": "Electronic overcurrent relays",
  "description": "I3MZ-WRAUWZ - Protection relay, EOCR Digital, 0.5 to 60A, 100 to 240VAC/DC, window connt, for motor protection.",
  "end_of_sale": null,
  "official_image_url": "https://download.schneider-electric.com/files?p_Doc_Ref=I3DM-WRDUWZ_IMG&p_File_Type=rendition_369_jpg&default_image=DefaultProductImage.png",
  "local_photo_path": "/docs/b8c9a9a7a8_photo.jpg",
  "image_confirmed_unavailable": false,
  "documents": [
    {
      "label": "Product datasheet",
      "official_url": "https://www.se.com/eg/en/product/download-pdf/I3MZ-WRAUWZ?filename=Schneider+Electric_EOCR_I3MZ-WRAUWZ.pdf",
      "local_path": "/docs/ef9de47dc1_product_datasheet.pdf"
    },
    {
      "label": "EOCR Catalog (English)",
      "official_url": "https://download.schneider-electric.com/files?p_enDocType=Catalog&p_File_Name=EOCR+catalog_EN.pdf&p_Doc_Ref=1588-2630",
      "local_path": "/docs/e100e2b2bb_eocr_catalog_english.pdf"
    }
  ],
  "source_url": "https://www.se.com/eg/en/product/I3MZ-WRAUWZ/protection-relay-eocr-digital-0-5-to-60a-100-to-240vac-dc-window-connt-for-motor-protection/",
  "scraped_at": "2026-06-28T03:29:14.618500+00:00",
  "category": null,
  "in_stock": true,
  "your_price": null,
  "your_notes": null
}